{
  "$schema": "https://json-schema.org/draft/2020-12/schema",
  "title": "create_local_backup",
  "type": "object",
  "properties": {
    "label": {
      "description": "Optional label appended to the filename, e.g. \"pre-upgrade\".",
      "type": "string"
    },
    "show_sensitive": {
      "default": false,
      "description": "Include secrets (keys/passwords) in the export. Default false.",
      "type": "boolean"
    },
    "verbose": {
      "default": false,
      "description": "Include every parameter, even defaults (RouterOS `verbose`).",
      "type": "boolean"
    },
    "compact": {
      "default": false,
      "description": "Export only non-default values (RouterOS `compact`; ignored if verbose).",
      "type": "boolean"
    },
    "terse": {
      "default": false,
      "description": "One self-contained, machine-readable line per item (RouterOS `terse`).",
      "type": "boolean"
    }
  },
  "required": [
    "show_sensitive",
    "verbose",
    "compact",
    "terse"
  ],
  "additionalProperties": false
}
